setup.py
arcade_game_center_api.egg-info/PKG-INFO
arcade_game_center_api.egg-info/SOURCES.txt
arcade_game_center_api.egg-info/dependency_links.txt
arcade_game_center_api.egg-info/requires.txt
arcade_game_center_api.egg-info/top_level.txt
arcapi/__init__.py
arcapi/api.py
arcapi/util.py