Metadata-Version: 1.0
Name: arcade-game-center-api
Version: 0.1.1
Summary: Korean Arcade game center API
Home-page: https://github.com/DSMdongly/Arcapi
Author: Toygrammer
Author-email: gdh0608@naver.com
License: MIT
Platform: UNKNOWN
